mace_descriptor/__init__.py
mace_descriptor/__version__.py
mace_descriptor/calculators/__init__.py
mace_descriptor/calculators/foundations_models.py
mace_descriptor/calculators/mace.py
mace_descriptor/data/__init__.py
mace_descriptor/data/atomic_data.py
mace_descriptor/data/neighborhood.py
mace_descriptor/data/utils.py
mace_descriptor/tools/__init__.py
mace_descriptor/tools/compile.py
mace_descriptor/tools/default_keys.py
mace_descriptor/tools/scripts_utils.py
mace_descriptor/tools/torch_tools.py
mace_descriptor/tools/utils.py
mace_descriptor/tools/torch_geometric/__init__.py
mace_descriptor/tools/torch_geometric/batch.py
mace_descriptor/tools/torch_geometric/data.py
mace_descriptor/tools/torch_geometric/dataloader.py
mace_descriptor/tools/torch_geometric/dataset.py
mace_descriptor/tools/torch_geometric/seed.py
mace_descriptor/tools/torch_geometric/utils.py
mace_descriptor-0.9.6.dist-info/licenses/LICENSE.md
mace_descriptor-0.9.6.dist-info/METADATA
mace_descriptor-0.9.6.dist-info/WHEEL
mace_descriptor-0.9.6.dist-info/top_level.txt
mace_descriptor-0.9.6.dist-info/RECORD
