Metadata-Version: 2.4
Name: mace-descriptor
Version: 0.9.6
Summary: Minimal fork of MACE for fast descriptor extraction from pretrained foundation models.
Home-page: https://github.com/InWonYeu/mace-descriptor
Author: In Won Yeu
License: MIT
Classifier: Programming Language :: Python :: 3
Classifier: Operating System :: OS Independent
Classifier: License :: OSI Approved :: MIT License
Requires-Python: >=3.7
License-File: LICENSE.md
Requires-Dist: torch>=1.12
Requires-Dist: e3nn==0.4.4
Requires-Dist: numpy
Requires-Dist: ase
Requires-Dist: matscipy
Provides-Extra: dev
Requires-Dist: black; extra == "dev"
Requires-Dist: isort; extra == "dev"
Requires-Dist: mypy; extra == "dev"
Requires-Dist: pre-commit; extra == "dev"
Requires-Dist: pytest; extra == "dev"
Dynamic: license-file
